{
  "id": "5526aec1e779896af9418262",
  "slug": "afterburn",
  "gameRef": "/Lotus/Powersuits/Dragon/DragonBreathAugmentCard",
  "tags": [
    "chroma",
    "mod",
    "warframe",
    "augment",
    "rare"
  ],
  "rarity": "rare",
  "maxRank": 3,
  "tradingTax": 8000,
  "tradable": true,
  "i18n": {
    "en": {
      "name": "Afterburn",
      "description": "Spectral Scream Augment: Upon deactivation, Chroma will launch an elemental projectile dealing 100 Damage for each second the ability was active, to a maximum of 500 Damage.",
      "wikiLink": "https://wiki.warframe.com/w/Afterburn",
      "icon": "items/images/en/afterburn.b80b09df8cb5238b9f09230b76a27d8a.png",
      "thumb": "items/images/en/thumbs/afterburn.b80b09df8cb5238b9f09230b76a27d8a.128x128.png"
    }
  }
}