{
  "id": "573b7fbd0ec44a47787a690d",
  "slug": "vauban_prime_blueprint",
  "gameRef": "/Lotus/Types/Recipes/WarframeRecipes/VaubanPrimeBlueprint",
  "tags": [
    "blueprint",
    "prime",
    "warframe"
  ],
  "setRoot": false,
  "setParts": [
    "573b7fbd0ec44a47787a690d",
    "573b7fc20ec44a47787a690e",
    "573b7fc80ec44a47787a690f",
    "573b7fcc0ec44a47787a6910",
    "573d0efa336297b2dfca2909"
  ],
  "quantityInSet": 1,
  "ducats": 65,
  "reqMasteryRank": 0,
  "tradingTax": 2000,
  "tradable": true,
  "i18n": {
    "en": {
      "name": "Vauban Prime Blueprint",
      "description": "Transform the battlefield into a weapon with this gilded tactician. Features unique mod polarities for extended customization.",
      "wikiLink": "https://wiki.warframe.com/w/Vauban_Prime",
      "icon": "items/images/en/vauban_prime_blueprint.9c15bb47d3ed4ed8e960c2502fac82f2.png",
      "thumb": "items/images/en/thumbs/vauban_prime_blueprint.9c15bb47d3ed4ed8e960c2502fac82f2.128x128.png",
      "subIcon": "sub_icons/blueprint_128x128.png"
    }
  }
}